toupie/__init__.py
toupie-0.1.0.dist-info/licenses/LICENSE.txt
toupie-0.1.0.dist-info/WHEEL
toupie-0.1.0.dist-info/entry_points.txt
toupie-0.1.0.dist-info/METADATA
toupie-0.1.0.dist-info/RECORD
