Metadata-Version: 2.4
Name: toupie
Version: 0.1.0
Summary: A Tiny Python Kernel
Author: Sébastien Boisgérault
Author-email: Sébastien Boisgérault <Sebastien.Boisgerault@gmail.com>
License-Expression: MIT
License-File: LICENSE.txt
Classifier: Programming Language :: Python :: 3
Classifier: Operating System :: OS Independent
Requires-Dist: flask>=3.1.1
Requires-Dist: raylib>=5.5.0.2
Requires-Dist: requests>=2.32.5
Requires-Dist: rich>=14.1.0
Requires-Dist: typer>=0.16.0
Requires-Dist: waitress>=3.0.2
Requires-Python: >=3.11
Project-URL: Homepage, https://github.com/boisgera/toupie
Project-URL: Issues, https://github.com/boisgera/toupie/issues
